atx/__init__.py
atx/_core.py
atx/cli.py
atx/prebuilds/__init__.py
atx/prebuilds/get_maps_geocode.py
atx/prebuilds/get_weather_forecast_daily.py
atx/prebuilds/hello_world.py
atx_py-0.0.2.dist-info/METADATA
atx_py-0.0.2.dist-info/WHEEL
atx_py-0.0.2.dist-info/entry_points.txt
atx_py-0.0.2.dist-info/licenses/LICENSE
atx_py-0.0.2.dist-info/RECORD
