Metadata-Version: 2.4
Name: atx-py
Version: 0.0.2
Summary: Aiello ToolX kit for Python
License: Private
License-File: LICENSE
Author: AllenChouAiello
Author-email: allen.chou@aiello.ai
Requires-Python: >=3.11,<4.0
Classifier: License :: Other/Proprietary License
Classifier: Programming Language :: Python :: 3
Classifier: Programming Language :: Python :: 3.11
Classifier: Programming Language :: Python :: 3.12
Classifier: Programming Language :: Python :: 3.13
Classifier: Programming Language :: Python :: 3.14
Provides-Extra: all
Requires-Dist: hot-tool (>=0.0.5,<1.0.0)
Requires-Dist: requests
